{"name":"Hook Any Text","tagline":"","body":"# What is HAT?\r\n\r\nHook Any Text is a plugin for Cheat Engine that automatically converts hexadecimal data into readable strings.\r\nThis project aims at providing a way to hook text when other widely used text hookers fail to do so.\r\nTherefore, it might not be as user-friendly as what is expected of such tools, and the result might not be as clean as you would expect.\r\nHowever, you WILL be able to hook the text of any game, even on emulators.\r\n\r\n# Installation\r\n\r\nFor all installation instructions, please visit [the wiki of the project](https://github.com/MX-Futhark/hook-any-text/wiki).","google":"","note":"Don't delete this file! It's used internally to help with page regeneration."}